[
  {
    "question": "Question 1",
    "answer": "Answer 1",
    "points": 100,
    "difficultyLevel": "hard",
    "answered": "pending"
  },
  {
    "question": "Question 2",
    "answer": "Answer 2",
    "points": 80,
    "difficultyLevel": "medium",
    "answered": "pending"
  },
  {
    "question": "Question 3",
    "answer": "Answer 3",
    "points": 60,
    "difficultyLevel": "easy",
    "answered": "pending"
  },
  {
    "question": "Question 4",
    "answer": "Answer 4",
    "points": 100,
    "difficultyLevel": "hard",
    "answered": "pending"
  },
  {
    "question": "Question 5",
    "answer": "Answer 5",
    "points": 80,
    "difficultyLevel": "medium",
    "answered": "pending"
  },
  {
    "question": "Question 6",
    "answer": "Answer 6",
    "points": 60,
    "difficultyLevel": "easy",
    "answered": "pending"
  },
  {
    "question": "Question 7",
    "answer": "Answer 7",
    "points": 100,
    "difficultyLevel": "hard",
    "answered": "pending"
  },
  {
    "question": "Question 8",
    "answer": "Answer 8",
    "points": 80,
    "difficultyLevel": "medium",
    "answered": "pending"
  },
  {
    "question": "Question 9",
    "answer": "Answer 9",
    "points": 60,
    "difficultyLevel": "easy",
    "answered": "pending"
  },
  {
    "question": "Question 10",
    "answer": "Answer 10",
    "points": 100,
    "difficultyLevel": "hard",
    "answered": "pending"
  },
  {
    "question": "Question 11",
    "answer": "Answer 11",
    "points": 80,
    "difficultyLevel": "medium",
    "answered": "pending"
  },
  {
    "question": "Question 12",
    "answer": "Answer 12",
    "points": 60,
    "difficultyLevel": "easy",
    "answered": "pending"
  },
  {
    "question": "Question 13",
    "answer": "Answer 13",
    "points": 100,
    "difficultyLevel": "hard",
    "answered": "pending"
  },
  {
    "question": "Question 14",
    "answer": "Answer 14",
    "points": 80,
    "difficultyLevel": "medium",
    "answered": "pending"
  },
  {
    "question": "Question 15",
    "answer": "Answer 15",
    "points": 60,
    "difficultyLevel": "easy",
    "answered": "pending"
  },
  {
    "question": "Question 16",
    "answer": "Answer 16",
    "points": 100,
    "difficultyLevel": "hard",
    "answered": "pending"
  },
  {
    "question": "Question 17",
    "answer": "Answer 17",
    "points": 80,
    "difficultyLevel": "medium",
    "answered": "pending"
  },
  {
    "question": "Question 18",
    "answer": "Answer 18",
    "points": 60,
    "difficultyLevel": "easy",
    "answered": "pending"
  },
  {
    "question": "Question 19",
    "answer": "Answer 19",
    "points": 100,
    "difficultyLevel": "hard",
    "answered": "pending"
  },
  {
    "question": "Question 20",
    "answer": "Answer 20",
    "points": 80,
    "difficultyLevel": "medium",
    "answered": "pending"
  },
  {
    "question": "Question 21",
    "answer": "Answer 21",
    "points": 60,
    "difficultyLevel": "easy",
    "answered": "pending"
  },
  {
    "question": "Question 22",
    "answer": "Answer 22",
    "points": 100,
    "difficultyLevel": "hard",
    "answered": "pending"
  },
  {
    "question": "Question 23",
    "answer": "Answer 23",
    "points": 80,
    "difficultyLevel": "medium",
    "answered": "pending"
  },
  {
    "question": "Question 24",
    "answer": "Answer 24",
    "points": 60,
    "difficultyLevel": "easy",
    "answered": "pending"
  },
  {
    "question": "Question 25",
    "answer": "Answer 25",
    "points": 100,
    "difficultyLevel": "hard",
    "answered": "pending"
  },
  {
    "question": "Question 26",
    "answer": "Answer 26",
    "points": 80,
    "difficultyLevel": "medium",
    "answered": "pending"
  },
  {
    "question": "Question 27",
    "answer": "Answer 27",
    "points": 60,
    "difficultyLevel": "easy",
    "answered": "pending"
  },
  {
    "question": "Question 28",
    "answer": "Answer 28",
    "points": 100,
    "difficultyLevel": "hard",
    "answered": "pending"
  },
  {
    "question": "Question 29",
    "answer": "Answer 29",
    "points": 80,
    "difficultyLevel": "medium",
    "answered": "pending"
  },
  {
    "question": "Question 30",
    "answer": "Answer 30",
    "points": 60,
    "difficultyLevel": "easy",
    "answered": "pending"
  },
  {
    "question": "Question 31",
    "answer": "Answer 31",
    "points": 100,
    "difficultyLevel": "hard",
    "answered": "pending"
  },
  {
    "question": "Question 32",
    "answer": "Answer 32",
    "points": 80,
    "difficultyLevel": "medium",
    "answered": "pending"
  },
  {
    "question": "Question 33",
    "answer": "Answer 33",
    "points": 60,
    "difficultyLevel": "easy",
    "answered": "pending"
  },
  {
    "question": "Question 34",
    "answer": "Answer 34",
    "points": 100,
    "difficultyLevel": "hard",
    "answered": "pending"
  },
  {
    "question": "Question 35",
    "answer": "Answer 35",
    "points": 80,
    "difficultyLevel": "medium",
    "answered": "pending"
  },
  {
    "question": "Question 36",
    "answer": "Answer 36",
    "points": 60,
    "difficultyLevel": "easy",
    "answered": "pending"
  },
  {
    "question": "Question 37",
    "answer": "Answer 37",
    "points": 100,
    "difficultyLevel": "hard",
    "answered": "pending"
  },
  {
    "question": "Question 38",
    "answer": "Answer 38",
    "points": 80,
    "difficultyLevel": "medium",
    "answered": "pending"
  },
  {
    "question": "Question 39",
    "answer": "Answer 39",
    "points": 60,
    "difficultyLevel": "easy",
    "answered": "pending"
  },
  {
    "question": "Question 40",
    "answer": "Answer 40",
    "points": 100,
    "difficultyLevel": "hard",
    "answered": "pending"
  },
  {
    "question": "Question 41",
    "answer": "Answer 41",
    "points": 80,
    "difficultyLevel": "medium",
    "answered": "pending"
  },
  {
    "question": "Question 42",
    "answer": "Answer 42",
    "points": 60,
    "difficultyLevel": "easy",
    "answered": "pending"
  },
  {
    "question": "Question 43",
    "answer": "Answer 43",
    "points": 100,
    "difficultyLevel": "hard",
    "answered": "pending"
  },
  {
    "question": "Question 44",
    "answer": "Answer 44",
    "points": 80,
    "difficultyLevel": "medium",
    "answered": "pending"
  },
  {
    "question": "Question 45",
    "answer": "Answer 45",
    "points": 60,
    "difficultyLevel": "easy",
    "answered": "pending"
  },
  {
    "question": "Question 46",
    "answer": "Answer 46",
    "points": 100,
    "difficultyLevel": "hard",
    "answered": "pending"
  },
  {
    "question": "Question 47",
    "answer": "Answer 47",
    "points": 80,
    "difficultyLevel": "medium",
    "answered": "pending"
  },
  {
    "question": "Question 48",
    "answer": "Answer 48",
    "points": 60,
    "difficultyLevel": "easy",
    "answered": "pending"
  },
  {
    "question": "Question 49",
    "answer": "Answer 49",
    "points": 100,
    "difficultyLevel": "hard",
    "answered": "pending"
  },
  {
    "question": "Question 50",
    "answer": "Answer 50",
    "points": 80,
    "difficultyLevel": "medium",
    "answered": "pending"
  }
]
